Metadata-Version: 1.0
Name: awsimagetag
Version: 1.6
Summary: AWS auto tagging tool
Home-page: https://pypi.org/project/aws-auto-tag-ami
Author: Jasper Culong
Author-email: jculongit10@yahoo.com
License: LICENSE
Platform: UNKNOWN
